fuzzy_fuss/__init__.py
fuzzy_fuss/fuzz/__init__.py
fuzzy_fuss/fuzz/defuzzifier.py
fuzzy_fuss/fuzz/func.py
fuzzy_fuss/fuzz/fuzzy4tuple.py
fuzzy_fuss/fuzz/fuzzy_rule.py
fuzzy_fuss/fuzz/fuzzy_rule_base.py
fuzzy_fuss/fuzz/fuzzy_set.py
fuzzy_fuss/fuzz/fuzzy_variable.py
fuzzy_fuss/misc/__init__.py
fuzzy_fuss/misc/plotting.py
fuzzy_fuss/rbs/__init__.py
fuzzy_fuss/rbs/parsed_object.py
fuzzy_fuss/rbs/parsed_rule.py
fuzzy_fuss/rbs/parsed_variable.py
fuzzy_fuss/rbs/rule_base_parser.py
fuzzy_fuss-0.0.1.dist-info/METADATA
fuzzy_fuss-0.0.1.dist-info/WHEEL
fuzzy_fuss-0.0.1.dist-info/top_level.txt
fuzzy_fuss-0.0.1.dist-info/RECORD
