Metadata-Version: 2.1
Name: fuzzy-fuss
Version: 0.0.1
Summary: Little fuzzy logic toolbox
Home-page: UNKNOWN
Author: Dominika Dlugosz
Author-email: dominika.a.m.dlugosz@gmail.com
License: UNKNOWN
Platform: UNKNOWN
Requires-Python: >=3.6
Requires-Dist: numpy (>=1.16)
Requires-Dist: matplotlib
Requires-Dist: pandas
